httpdiff/__init__.py
httpdiff/baseline.py
httpdiff/blob.py
httpdiff/response.py
httpdiff-1.1.0.dist-info/LICENSE
httpdiff-1.1.0.dist-info/METADATA
httpdiff-1.1.0.dist-info/WHEEL
httpdiff-1.1.0.dist-info/top_level.txt
httpdiff-1.1.0.dist-info/RECORD
