Metadata-Version: 2.1
Name: httpdiff
Version: 1.1.0
Summary: HTTPDiff - Finding differences between HTTP responses
Home-page: UNKNOWN
Author: William Kristoffersen
Author-email: william.kristof@gmail.com
License: MIT
Keywords: python,httpdiff
Platform: UNKNOWN
License-File: LICENSE
Requires-Dist: rapidfuzz
